BuildSimHubAPI/__init__.py
BuildSimHubAPI/buildsimhub.py
BuildSimHubAPI/info.config
BuildSimHubAPI/version.py
BuildSimHubAPI/experiment/AHU_builder.py
BuildSimHubAPI/experiment/__init__.py
BuildSimHubAPI/experiment/hvac_component.py
BuildSimHubAPI/experiment/water_loop_builder.py
BuildSimHubAPI/experiment/water_loop_component.py
BuildSimHubAPI/helpers/__init__.py
BuildSimHubAPI/helpers/bldgsim_info.py
BuildSimHubAPI/helpers/class_template.py
BuildSimHubAPI/helpers/compat.py
BuildSimHubAPI/helpers/design_template.py
BuildSimHubAPI/helpers/energy_model.py
BuildSimHubAPI/helpers/eplus_object.py
BuildSimHubAPI/helpers/httpurllib.py
BuildSimHubAPI/helpers/network_connectivity.py
BuildSimHubAPI/helpers/parametric_job.py
BuildSimHubAPI/helpers/parametric_model.py
BuildSimHubAPI/helpers/simulation_job.py
BuildSimHubAPI/helpers/simulation_type.py
BuildSimHubAPI/htmlParser/__init__.py
BuildSimHubAPI/htmlParser/html_utility.py
BuildSimHubAPI/htmlParser/numeric_value_parser.py
BuildSimHubAPI/logger/__init__.py
BuildSimHubAPI/logger/logger.py
BuildSimHubAPI/measures/__init__.py
BuildSimHubAPI/measures/bldg_orientation.py
BuildSimHubAPI/measures/cooling_all_cop.py
BuildSimHubAPI/measures/cooling_chiller_cop.py
BuildSimHubAPI/measures/cooling_coil_cop.py
BuildSimHubAPI/measures/customized_measure.py
BuildSimHubAPI/measures/daylit_sensor.py
BuildSimHubAPI/measures/demand_control.py
BuildSimHubAPI/measures/discrete_measure_option_template.py
BuildSimHubAPI/measures/displacement_ventilation.py
BuildSimHubAPI/measures/equipment_epd.py
BuildSimHubAPI/measures/equipment_epd_percent.py
BuildSimHubAPI/measures/heat_recovery.py
BuildSimHubAPI/measures/heating_dx_efficiency.py
BuildSimHubAPI/measures/heating_efficiency.py
BuildSimHubAPI/measures/hvac_template.py
BuildSimHubAPI/measures/infiltration.py
BuildSimHubAPI/measures/light_lpd.py
BuildSimHubAPI/measures/light_lpd_percent.py
BuildSimHubAPI/measures/model_action.py
BuildSimHubAPI-2.0.0.dist-info/METADATA
BuildSimHubAPI-2.0.0.dist-info/RECORD
BuildSimHubAPI-2.0.0.dist-info/WHEEL
BuildSimHubAPI-2.0.0.dist-info/top_level.txt
