Metadata-Version: 2.1
Name: BuildSimHubAPI
Version: 2.0.0
Summary: BuildSim Cloud API library for Python
Home-page: https://github.com/weilix88/buildsimhub_python_api
Author: Weili Xu, Haopeng Wang
Author-email: weili.xu@buildsimhub.net
License: MIT
Platform: UNKNOWN
Classifier: Programming Language :: Python :: 3.5
Classifier: Programming Language :: Python :: 3.6
